masgent/__init__.py
masgent/cli.py
masgent/ai_mode/__init__.py
masgent/ai_mode/ai_backend.py
masgent/ai_mode/system_prompt.txt
masgent/cli_mode/__init__.py
masgent/cli_mode/cli_entries.py
masgent/cli_mode/cli_run.py
masgent/res/ml_db_AlMgSiSc.pkl
masgent/res/ml_nn_AlCoCrFeNi.pkl
masgent/res/ml_nn_AlMgSiSc.pkl
masgent/res/ml_xs_AlCoCrFeNi.pkl
masgent/res/ml_xs_AlMgSiSc.pkl
masgent/res/ml_ys_AlCoCrFeNi.pkl
masgent/res/ml_ys_AlMgSiSc.pkl
masgent/utils/__init__.py
masgent/utils/interface_maker.py
masgent/utils/ml_cvae.py
masgent/utils/ml_nn_design.py
masgent/utils/ml_nn_train.py
masgent/utils/schemas.py
masgent/utils/tools.py
masgent/utils/utils.py
masgent-1.1.19.dist-info/licenses/LICENSE
masgent-1.1.19.dist-info/METADATA
masgent-1.1.19.dist-info/WHEEL
masgent-1.1.19.dist-info/entry_points.txt
masgent-1.1.19.dist-info/top_level.txt
masgent-1.1.19.dist-info/RECORD
