Metadata-Version: 2.4
Name: masgent
Version: 1.1.19
Summary: Masgent: Materials Simulation Agent
Author-email: Guangchen Liu <gliu4@wpi.edu>
Maintainer-email: Guangchen Liu <gliu4@wpi.edu>
License: MIT
Project-URL: Homepage, https://github.com/aguang5241/masgent
Project-URL: Issues, https://github.com/aguang5241/masgent/issues
Project-URL: Repository, https://github.com/aguang5241/masgent
Keywords: AI agent,Materials Simulation,Density Functional Theory,Machine Learning Potentials,Machine Learning
Requires-Python: <3.14,>=3.11
License-File: LICENSE
Requires-Dist: ase
Requires-Dist: numpy
Requires-Dist: pandas
Requires-Dist: scipy
Requires-Dist: scikit-learn
Requires-Dist: matplotlib
Requires-Dist: seaborn
Requires-Dist: pydantic_ai
Requires-Dist: pymatgen
Requires-Dist: pymatgen-analysis-defects
Requires-Dist: mp-api
Requires-Dist: dotenv
Requires-Dist: colorama
Requires-Dist: bullet
Requires-Dist: yaspin
Requires-Dist: icet
Requires-Dist: sevenn
Requires-Dist: chgnet
Requires-Dist: orb-models
Requires-Dist: mattersim
Requires-Dist: optuna
Provides-Extra: dev
Requires-Dist: build; extra == "dev"
Requires-Dist: twine; extra == "dev"
Provides-Extra: docs
Dynamic: license-file
